circe/__init__.py
circe/cohort_expression.py
circe/cohort_sql_builder.py
circe/concept_set_expression.py
circe/concept_set_sql_builder.py
circe/print_friendly.py
circe/data/conceptSet.json
circe/data/conceptSetList.json
circe/data/simpleCohort.json
circe/java/animal-sniffer-annotations-1.14.jar
circe/java/asm-6.2.1.jar
circe/java/asm-analysis-6.2.1.jar
circe/java/asm-commons-6.2.1.jar
circe/java/asm-tree-6.2.1.jar
circe/java/asm-util-6.2.1.jar
circe/java/checker-qual-2.0.0.jar
circe/java/circe-1.10.1.jar
circe/java/commons-io-2.7.jar
circe/java/commons-lang3-3.6.jar
circe/java/error_prone_annotations-2.1.3.jar
circe/java/freemarker-2.3.30.jar
circe/java/graal-sdk-1.0.0-rc15.jar
circe/java/guava-25.1-jre.jar
circe/java/icu4j-62.1.jar
circe/java/j2objc-annotations-1.1.jar
circe/java/jackson-annotations-2.9.9.jar
circe/java/jackson-core-2.9.10.jar
circe/java/jackson-databind-2.9.10.7.jar
circe/java/java-semver-0.9.0.jar
circe/java/js-1.0.0-rc15.jar
circe/java/js-scriptengine-1.0.0-rc15.jar
circe/java/jsr305-3.0.2.jar
circe/java/regex-1.0.0-rc15.jar
circe/java/standardized-analysis-utils-1.3.0.jar
circe/java/truffle-api-1.0.0-rc15.jar
python_circe-0.0.4.dist-info/LICENSE
python_circe-0.0.4.dist-info/METADATA
python_circe-0.0.4.dist-info/WHEEL
python_circe-0.0.4.dist-info/top_level.txt
python_circe-0.0.4.dist-info/RECORD
