Metadata-Version: 2.1
Name: python-circe
Version: 0.0.4
Summary: Python wrapper for Circe
Requires-Python: >=3.10
License-File: LICENSE
Requires-Dist: jpype1 (==1.4.1)
